pafy/__init__.py
pafy/backend_internal.py
pafy/backend_shared.py
pafy/backend_youtube_dl.py
pafy/channel.py
pafy/g.py
pafy/jsinterp.py
pafy/pafy.py
pafy/playlist.py
pafy/util.py
pafy_tmsl-0.5.6.data/scripts/ytdl
pafy_tmsl-0.5.6.dist-info/AUTHORS
pafy_tmsl-0.5.6.dist-info/LICENSE
pafy_tmsl-0.5.6.dist-info/METADATA
pafy_tmsl-0.5.6.dist-info/WHEEL
pafy_tmsl-0.5.6.dist-info/top_level.txt
pafy_tmsl-0.5.6.dist-info/RECORD
